Metadata-Version: 1.1
Name: nasdaqesgpy
Version: 0.0.0
Summary: This is a very basic library that would give internal users access to our scraping efforts.
Home-page: UNKNOWN
Author: Viktor Aghajanyan
Author-email: aghajanyanviktor@gmail.com
License: MIT
Keywords: napp
Platform: UNKNOWN
Classifier: Development Status :: 5 - Production/Stable
Classifier: Intended Audience :: Education
Classifier: Operating System :: Microsoft :: Windows :: Windows 10
Classifier: License :: OSI Approved :: MIT License
Classifier: Programming Language :: Python :: 3
